{"type":"FeatureCollection","features":[{"type":"Feature","properties":[{"building":"house"},{"source":"NextView"}],"geometry":{"type":"LineString","coordinates":[["85.2935769","27.6726864"],["85.2935769","27.6726215"],["85.2936304","27.6726215"],["85.2936284","27.6726846"],["85.2935769","27.6726864"]]}},{"type":"Feature","properties":[{"building":"house"},{"source":"NextView"}],"geometry":{"type":"LineString","coordinates":[["85.2972233","27.6731986"],["85.2971862","27.6731379"],["85.2972033","27.6731176"],["85.2972605","27.6731733"],["85.2972233","27.6731986"]]}},{"type":"Feature","properties":[{"building":"house"},{"source":"NextView"}],"geometry":{"type":"LineString","coordinates":[["85.2953479","27.6736088"],["85.2953651","27.6736771"],["85.2954451","27.6736696"],["85.2954337","27.6736012"],["85.2953479","27.6736088"]]}}]}