{"type":"FeatureCollection","features":[{"type":"Feature","properties":[],"geometry":{"type":"LineString","coordinates":[["85.9822262","27.5838774"],["85.9820259","27.5837736"],["85.982219","27.5836214"],["85.982498","27.5837165"],["85.9828628","27.5838687"],["85.983013","27.5838116"],["85.9831846","27.5838497"]]}},{"type":"Feature","properties":[],"geometry":{"type":"LineString","coordinates":[["85.9831846","27.5838497"],["85.9833348","27.5837926"]]}},{"type":"Feature","properties":[],"geometry":{"type":"LineString","coordinates":[["85.9835494","27.5837356"],["85.9838284","27.5839257"],["85.9841288","27.5838687"]]}},{"type":"Feature","properties":[],"geometry":{"type":"LineString","coordinates":[["85.9841288","27.5838687"],["85.9842575","27.5837736"]]}},{"type":"Feature","properties":[],"geometry":{"type":"LineString","coordinates":[["85.9842575","27.5837736"],["85.984279","27.5827276"]]}},{"type":"Feature","properties":[],"geometry":{"type":"LineString","coordinates":[["85.9833348","27.5837926"],["85.9835494","27.5837356"]]}},{"type":"Feature","properties":[{"highway":"road"}],"geometry":{"type":"LineString","coordinates":[["85.9842790","27.5827276"],["85.9842825","27.5826016"],["85.9841966","27.5824875"],["85.984261","27.5823924"],["85.9844541","27.5823924"],["85.9845829","27.5824875"]]}},{"type":"Feature","properties":[{"highway":"road"}],"geometry":{"type":"LineString","coordinates":[["85.9845829","27.5824875"],["85.9847331","27.5825636"]]}},{"type":"Feature","properties":[{"highway":"road"}],"geometry":{"type":"LineString","coordinates":[["85.9847331","27.5825636"],["85.9849048","27.5825446"]]}},{"type":"Feature","properties":[{"highway":"road"}],"geometry":{"type":"LineString","coordinates":[["85.9849048","27.5825446"],["85.985055","27.5823924"],["85.985012","27.5821452"],["85.9849262","27.581993"]]}},{"type":"Feature","properties":[{"highway":"road"}],"geometry":{"type":"LineString","coordinates":[["85.9849262","27.581993"],["85.9847975","27.5817838"],["85.9851408","27.5815366"],["85.9851837","27.5814034"],["85.9851837","27.5812893"],["85.9851837","27.5811371"]]}},{"type":"Feature","properties":[{"highway":"road"}],"geometry":{"type":"LineString","coordinates":[["85.9842790","27.5827276"],["85.9842825","27.5826016"],["85.9841752","27.5825065"]]}},{"type":"Feature","properties":[{"highway":"road"}],"geometry":{"type":"LineString","coordinates":[["85.9851837","27.5811371"],["85.9851936","27.5810325"],["85.9851887","27.5809845"],["85.9851542","27.5808601"],["85.9851198","27.5808056"],["85.9850903","27.580738"],["85.9850435","27.5806878"],["85.9850238","27.580642"],["85.9850041","27.5806005"],["85.9849721","27.5805372"],["85.9849573","27.5804762"],["85.9849893","27.5804456"],["85.9850386","27.5804827"]]}},{"type":"Feature","properties":[],"geometry":{"type":"LineString","coordinates":[["85.9822262","27.5838774"],["85.9820259","27.5837736"],["85.982219","27.5836214"],["85.982498","27.5837165"],["85.9828628","27.5838687"],["85.983013","27.5838116"],["85.9831846","27.5838497"]]}},{"type":"Feature","properties":[],"geometry":{"type":"LineString","coordinates":[["85.9831846","27.5838497"],["85.9833348","27.5837926"]]}},{"type":"Feature","properties":[],"geometry":{"type":"LineString","coordinates":[["85.9835494","27.5837356"],["85.9838284","27.5839257"],["85.9841288","27.5838687"]]}},{"type":"Feature","properties":[],"geometry":{"type":"LineString","coordinates":[["85.9841288","27.5838687"],["85.9842575","27.5837736"]]}},{"type":"Feature","properties":[],"geometry":{"type":"LineString","coordinates":[["85.9842575","27.5837736"],["85.984279","27.5827276"]]}},{"type":"Feature","properties":[],"geometry":{"type":"LineString","coordinates":[["85.9833348","27.5837926"],["85.9835494","27.5837356"]]}},{"type":"Feature","properties":[{"highway":"road"}],"geometry":{"type":"LineString","coordinates":[["85.984279","27.5827276"],["85.9842825","27.5826016"],["85.9841966","27.5824875"],["85.984261","27.5823924"],["85.9844541","27.5823924"],["85.9845829","27.5824875"]]}},{"type":"Feature","properties":[{"highway":"road"}],"geometry":{"type":"LineString","coordinates":[["85.9845829","27.5824875"],["85.9847331","27.5825636"]]}},{"type":"Feature","properties":[{"highway":"road"}],"geometry":{"type":"LineString","coordinates":[["85.9847331","27.5825636"],["85.9849048","27.5825446"]]}},{"type":"Feature","properties":[{"highway":"road"}],"geometry":{"type":"LineString","coordinates":[["85.9849048","27.5825446"],["85.985055","27.5823924"],["85.985012","27.5821452"],["85.9849262","27.581993"]]}},{"type":"Feature","properties":[{"highway":"road"}],"geometry":{"type":"LineString","coordinates":[["85.9849262","27.581993"],["85.9847975","27.5817838"],["85.9851408","27.5815366"],["85.9851837","27.5814034"],["85.9851837","27.5812893"],["85.9851837","27.5811371"]]}},{"type":"Feature","properties":[{"highway":"road"}],"geometry":{"type":"LineString","coordinates":[["85.984279","27.5827276"],["85.9842825","27.5826016"],["85.9841752","27.5825065"]]}},{"type":"Feature","properties":[{"highway":"road"}],"geometry":{"type":"LineString","coordinates":[["85.9851837","27.5811371"],["85.9851936","27.5810325"],["85.9851887","27.5809845"],["85.9851542","27.5808601"],["85.9851198","27.5808056"],["85.9850903","27.580738"],["85.9850435","27.5806878"],["85.9850238","27.580642"],["85.9850041","27.5806005"],["85.9849721","27.5805372"],["85.9849573","27.5804762"],["85.9849893","27.5804456"],["85.9850386","27.5804827"]]}},{"type":"Feature","properties":[{"highway":"unclassified"}],"geometry":{"type":"LineString","coordinates":[["85.6135875","27.4109003"],["85.6135875","27.4112066"],["85.6135875","27.4114229"],["85.6134251","27.411513"]]}},{"type":"Feature","properties":[],"geometry":{"type":"LineString","coordinates":[["85.6134251","27.411513"],["85.6133439","27.4117112"],["85.6134251","27.4118734"]]}},{"type":"Feature","properties":[{"highway":"unclassified"}],"geometry":{"type":"LineString","coordinates":[["85.6134251","27.4118734"],["85.6134382","27.4119429"]]}},{"type":"Feature","properties":[{"highway":"unclassified"}],"geometry":{"type":"LineString","coordinates":[["85.6134382","27.4119429"],["85.6134462","27.4119787"]]}},{"type":"Feature","properties":[],"geometry":{"type":"LineString","coordinates":[["85.613476","27.4115328"],["85.613387","27.4116263"],["85.6133768","27.4116946"],["85.6134251","27.4118734"]]}},{"type":"Feature","properties":[{"highway":"unclassified"}],"geometry":{"type":"LineString","coordinates":[["85.6134462","27.4119787"],["85.6134385","27.4119942"],["85.6134506","27.4120085"],["85.6134613","27.4120251"],["85.6134573","27.412043"],["85.61346","27.4120644"],["85.6134492","27.4120811"],["85.6134358","27.4120942"],["85.6134278","27.4121025"],["85.6134197","27.4121263"],["85.6134197","27.4121394"],["85.613409","27.4121537"]]}},{"type":"Feature","properties":[{"highway":"unclassified"}],"geometry":{"type":"LineString","coordinates":[["85.613409","27.4121537"],["85.6133996","27.4121692"],["85.6134009","27.4121847"],["85.6134009","27.4122037"],["85.6133942","27.4122168"],["85.6133849","27.4122371"],["85.6133714","27.4122442"]]}},{"type":"Feature","properties":[{"highway":"unclassified"}],"geometry":{"type":"LineString","coordinates":[["85.6133714","27.4122442"],["85.6133728","27.4122585"]]}},{"type":"Feature","properties":[{"highway":"unclassified"}],"geometry":{"type":"LineString","coordinates":[["85.6133714","27.4122442"],["85.6133728","27.4122585"],["85.6133741","27.4122728"],["85.6133741","27.4122894"],["85.6133755","27.4123049"],["85.6133634","27.4123192"],["85.6133419","27.4123311"],["85.6133258","27.4123371"],["85.6133097","27.4123454"],["85.6132937","27.4123668"]]}},{"type":"Feature","properties":[{"highway":"unclassified"}],"geometry":{"type":"LineString","coordinates":[["85.6132937","27.4123668"],["85.6132908","27.4123976"],["85.6132941","27.4124168"],["85.6132875","27.4124301"]]}},{"type":"Feature","properties":[{"highway":"unclassified"}],"geometry":{"type":"LineString","coordinates":[["85.6133714","27.4122442"],["85.6133728","27.4122585"],["85.6133741","27.4122728"],["85.6133674","27.4123126"],["85.6133576","27.4123213"],["85.6133419","27.4123311"],["85.6133258","27.4123371"],["85.6133097","27.4123454"],["85.6132937","27.4123668"]]}},{"type":"Feature","properties":[{"highway":"unclassified"}],"geometry":{"type":"LineString","coordinates":[["85.6132875","27.4124301"],["85.6132784","27.4124505"]]}},{"type":"Feature","properties":[{"highway":"unclassified"}],"geometry":{"type":"LineString","coordinates":[["85.6132784","27.4124505"],["85.6132762","27.412473"],["85.6132762","27.4124849"]]}},{"type":"Feature","properties":[{"highway":"unclassified"}],"geometry":{"type":"LineString","coordinates":[["86.1540905","27.3716054"],["86.1539912","27.3713892"],["86.1538732","27.3712082"],["86.1539054","27.3710462"],["86.1539697","27.3709033"],["86.1540234","27.3707604"],["86.1540234","27.3706556"],["86.1540234","27.3705413"],["86.1539268","27.3704174"],["86.153841","27.3703221"],["86.1538195","27.3702459"],["86.153841","27.3701602"],["86.1538946","27.3700744"],["86.1539268","27.3699315"],["86.1539805","27.3697505"],["86.1540449","27.3695408"],["86.1540341","27.3693884"],["86.153959","27.3692741"],["86.1538946","27.3694456"],["86.1538517","27.3695504"],["86.1537874","27.3696075"],["86.1537337","27.3696933"],["86.1536908","27.3698172"],["86.1536264","27.3699029"],["86.1535728","27.3700077"],["86.153487","27.3700268"],["86.1534011","27.3701411"],["86.153326","27.3702268"],["86.1532831","27.3703983"],["86.1532187","27.3704746"]]}},{"type":"Feature","properties":[{"highway":"unclassified"}],"geometry":{"type":"LineString","coordinates":[["86.153959","27.3692741"],["86.1540234","27.369074"],["86.1541414","27.3689025"],["86.1542594","27.3686071"],["86.1543238","27.368407"],["86.1543453","27.3682736"],["86.1543774","27.3681498"],["86.1543774","27.3680068"],["86.1544311","27.367902"],["86.1545169","27.3677591"],["86.1545706","27.3676543"],["86.1545598","27.367559"],["86.1545169","27.3674638"],["86.1545276","27.3673304"],["86.1546135","27.3672256"],["86.1546135","27.3671398"],["86.1546564","27.3670731"],["86.1547315","27.3669492"],["86.154871","27.3669397"],["86.1549461","27.3669016"],["86.1550963","27.366873"],["86.1553001","27.3668158"],["86.1554611","27.3667396"]]}},{"type":"Feature","properties":[{"highway":"unclassified"}],"geometry":{"type":"LineString","coordinates":[["86.1554611","27.3667396"],["86.1556327","27.366692"],["86.1557722","27.366692"],["86.1559331","27.3667777"]]}},{"type":"Feature","properties":[{"highway":"unclassified"}],"geometry":{"type":"LineString","coordinates":[["86.1559331","27.3667777"],["86.1559573","27.3667914"],["86.1559975","27.3668129"],["86.1560203","27.3668295"],["86.1560471","27.3668438"],["86.1560579","27.3668688"],["86.1560632","27.3668819"],["86.1560632","27.3668927"]]}},{"type":"Feature","properties":[{"highway":"unclassified"}],"geometry":{"type":"LineString","coordinates":[["86.1560632","27.3668927"],["86.1560552","27.3669105"],["86.1560445","27.3669165"],["86.1560324","27.3669272"],["86.1560069","27.3669272"],["86.1559761","27.366926"],["86.1559425","27.366926"],["86.155909","27.366926"],["86.1558768","27.366926"],["86.1558446","27.3669308"],["86.1558044","27.3669379"],["86.1557736","27.3669558"],["86.1557454","27.3669641"],["86.1557213","27.3669808"],["86.1556998","27.3669939"],["86.1556743","27.3670034"],["86.1556555","27.3670201"]]}},{"type":"Feature","properties":[{"highway":"unclassified"}],"geometry":{"type":"LineString","coordinates":[["86.1556555","27.3670201"],["86.1556151","27.3670375"],["86.1555701","27.3670557"],["86.1555251","27.3670811"],["86.1554965","27.3670932"],["86.1554515","27.3671223"],["86.1554243","27.3671356"],["86.1553861","27.3671622"],["86.155352","27.3671743"],["86.1553111","27.3671985"],["86.1552457","27.3672215"],["86.1552185","27.3672276"],["86.1551748","27.3672385"],["86.1551353","27.3672518"],["86.155104","27.3672627"],["86.1550767","27.3672784"],["86.1550644","27.3672857"]]}},{"type":"Feature","properties":[{"highway":"unclassified"}],"geometry":{"type":"LineString","coordinates":[["86.1550767","27.3672784"],["86.1550644","27.3672857"],["86.1550576","27.3673123"],["86.1550385","27.3673365"],["86.1550372","27.3673595"],["86.1550372","27.3673801"],["86.1550399","27.3674007"],["86.1550413","27.3674237"],["86.1550508","27.3674515"],["86.1550535","27.3674842"],["86.1550603","27.367506"],["86.1550631","27.367535"],["86.1550644","27.367558"],["86.155074","27.3675823"],["86.1550753","27.3675944"]]}},{"type":"Feature","properties":[{"highway":"unclassified"}],"geometry":{"type":"LineString","coordinates":[["86.1550753","27.3675944"],["86.1550748","27.3676083"],["86.1550786","27.3676307"],["86.1550938","27.3676712"],["86.1551127","27.367706"],["86.1551254","27.3677465"],["86.1551355","27.3677678"],["86.1551343","27.3677836"],["86.1551444","27.3677948"],["86.1551558","27.3678161"]]}},{"type":"Feature","properties":[{"highway":"unclassified"}],"geometry":{"type":"LineString","coordinates":[["86.2032715","27.5448211"],["86.2031185","27.544776"],["86.2030327","27.5448236"],["86.2029469","27.5448617"]]}},{"type":"Feature","properties":[{"highway":"unclassified"}],"geometry":{"type":"LineString","coordinates":[["86.2029469","27.5448617"],["86.2030621","27.5448073"]]}},{"type":"Feature","properties":[{"highway":"unclassified"}],"geometry":{"type":"LineString","coordinates":[["86.2029469","27.5448617"],["86.2029096","27.5449077"],["86.2028385","27.5449351"],["86.2027728","27.5449862"],["86.2027446","27.5450243"],["86.2027165","27.5450671"],["86.202695","27.5451254"],["86.202695","27.5451682"],["86.2027111","27.5452282"],["86.2027232","27.5452746"],["86.2027285","27.5453156"]]}},{"type":"Feature","properties":[{"highway":"unclassified"}],"geometry":{"type":"LineString","coordinates":[["86.2027285","27.5453156"],["86.2027272","27.5453923"]]}},{"type":"Feature","properties":[{"highway":"unclassified"}],"geometry":{"type":"LineString","coordinates":[["86.2027272","27.5453923"],["86.2027218","27.5454755"],["86.2027178","27.5455493"],["86.2027097","27.5456135"],["86.2026937","27.5457098"],["86.2026507","27.5458656"],["86.2026186","27.5459357"],["86.202585","27.5459559"],["86.2025475","27.5459964"],["86.2025126","27.5460261"],["86.2024938","27.546057"],["86.2024684","27.5460879"],["86.2024549","27.5461367"],["86.2024469","27.5461735"],["86.2024429","27.5462229"],["86.2024409","27.5462562"],["86.2024395","27.5462859"],["86.2024368","27.546318"],["86.2024362","27.5463317"]]}},{"type":"Feature","properties":[{"highway":"road"}],"geometry":{"type":"LineString","coordinates":[["86.2088066","27.5463498"],["86.2087102","27.5459035"],["86.2086467","27.5457064"],["86.2078525","27.5454388"],["86.2077414","27.5451431"],["86.2080273","27.5447910"],["86.2079637","27.5444953"],["86.2074555","27.5445798"],["86.2071378","27.5445375"],["86.2068519","27.5445938"],["86.2065501","27.5446361"],["86.2063754","27.5447488"],["86.2061689","27.5445375"],["86.2059466","27.5441573"],["86.2058354","27.5438475"],["86.2056764","27.5436782"],["86.2053424","27.5438193"],["86.2050720","27.5437911"],["86.2047062","27.5440026"],["86.2043404","27.5440449"],["86.2038950","27.5442564"],["86.2038186","27.5446274"],["86.2038186","27.5446785"],["86.203814","27.544688"],["86.2038079","27.5447511"],["86.2037583","27.544801"],["86.2032715","27.5448211"]]}},{"type":"Feature","properties":[{"highway":"unclassified"}],"geometry":{"type":"LineString","coordinates":[["86.2032715","27.5448211"],["86.2031645","27.5447971"],["86.2031185","27.544776"],["86.2030621","27.5448073"],["86.2030327","27.5448236"],["86.2029797","27.5448679"]]}},{"type":"Feature","properties":[{"highway":"unclassified"}],"geometry":{"type":"LineString","coordinates":[["86.2024362","27.5463317"],["86.2024234","27.546373"],["86.2024073","27.5464146"],["86.2023644","27.5464895"],["86.2023349","27.5465549"],["86.202288","27.5466358"],["86.2022491","27.5467345"],["86.2022169","27.5468094"],["86.2021673","27.5468914"],["86.2021257","27.5469533"],["86.2020667","27.5469818"],["86.2020211","27.5469961"],["86.2019567","27.5470044"],["86.2019071","27.5469937"],["86.2018521","27.5469842"],["86.2017998","27.546977"]]}}]}